crystex/__init__.py
crystex/coordgeometry.py
crystex/dream3d.py
crystex/fileutils.py
crystex/lattice.py
crystex/misorientations.py
crystex/numutils.py
crystex/plots.py
crystex/projections.py
crystex/rotations.py
crystex/symmetry.py
crystex-0.1.0.dist-info/METADATA
crystex-0.1.0.dist-info/WHEEL
crystex-0.1.0.dist-info/top_level.txt
crystex-0.1.0.dist-info/RECORD
